unhealpix.py
unhealpix-2.0.0.dist-info/METADATA
unhealpix-2.0.0.dist-info/WHEEL
unhealpix-2.0.0.dist-info/entry_points.txt
unhealpix-2.0.0.dist-info/top_level.txt
unhealpix-2.0.0.dist-info/RECORD
