Metadata-Version: 2.1
Name: unhealpix
Version: 2.0.0
Summary: Reproject healpix FITS images.
Home-page: https://github.com/AlecThomson/unhealpix
Author: Alec Thomson
Author-email: alec.thomson@csiro.au
License: MIT
Platform: UNKNOWN
Classifier: License :: OSI Approved :: MIT License
Classifier: Programming Language :: Python
Classifier: Programming Language :: Python :: 3
Classifier: Programming Language :: Python :: 3.6
Classifier: Programming Language :: Python :: Implementation :: CPython
Requires-Python: >=3.6.0
Requires-Dist: astropy
Requires-Dist: reproject
